uncertaintylib/__init__.py
uncertaintylib/plot_functions.py
uncertaintylib/uncertainty_functions.py
uncertaintylib-1.0.1.dist-info/licenses/LICENSE
uncertaintylib-1.0.1.dist-info/METADATA
uncertaintylib-1.0.1.dist-info/WHEEL
uncertaintylib-1.0.1.dist-info/top_level.txt
uncertaintylib-1.0.1.dist-info/RECORD
