Metadata-Version: 2.4
Name: uncertaintylib
Version: 1.0.1
Summary: A library containing functions used for estimating uncertainties
Home-page: https://github.com/equinor/uncertaintylib
Author: Christian Hågenvik
Author-email: chaagen2013@gmail.com
License: MIT
Keywords: uncertainty,uncertainty analysis,uncertainty estimation,uncertainty quantification
Classifier: Programming Language :: Python :: 3
Classifier: License :: OSI Approved :: MIT License
Classifier: Operating System :: OS Independent
Requires-Python: >=3.9
License-File: LICENSE
Requires-Dist: numpy
Requires-Dist: scipy
Requires-Dist: pandas
Requires-Dist: matplotlib
Dynamic: author
Dynamic: author-email
Dynamic: classifier
Dynamic: description
Dynamic: description-content-type
Dynamic: home-page
Dynamic: keywords
Dynamic: license
Dynamic: license-file
Dynamic: requires-dist
Dynamic: requires-python
Dynamic: summary
